<annotation>
	<folder>New</folder>
	<filename>image8.jpg</filename>
	<path>C:\Users\Kirti\Desktop\New\image8.jpg</path>
	<source>
		<database>Unknown</database>
	</source>
	<size>
		<width>450</width>
		<height>400</height>
		<depth>3</depth>
	</size>
	<segmented>0</segmented>
	<object>
		<name>with_mask</name>
		<pose>Unspecified</pose>
		<truncated>0</truncated>
		<difficult>0</difficult>
		<bndbox>
			<xmin>23</xmin>
			<ymin>101</ymin>
			<xmax>348</xmax>
			<ymax>381</ymax>
		</bndbox>
	</object>
</annotation>
